Metadata-Version: 1.0
Name: cosima-cookbook
Version: 0.2
Summary: Diagnostics for COSIMA: Consortium for Ocean-Sea Ice Modelling in Australia
Home-page: https://github.com/OceansAus/cosima-cookbook
Author: James Munroe
Author-email: jmunroe@mun.ca
License: Apache License 2.0
Platform: UNKNOWN
